stackcrawler/__init__.py
stackcrawler/stackcrawler.py
stackcrawler-1.0.dist-info/LICENSE
stackcrawler-1.0.dist-info/METADATA
stackcrawler-1.0.dist-info/WHEEL
stackcrawler-1.0.dist-info/top_level.txt
stackcrawler-1.0.dist-info/RECORD
