Metadata-Version: 2.1
Name: stackcrawler
Version: 1.0
Summary: UNKNOWN
Home-page: UNKNOWN
Author: Ashok Kumar
Author-email: ashbhati2@gmail.com
License: UNKNOWN
Platform: UNKNOWN
